pyyt/__init__.py
pyyt/config.py
pyyt/downloader.py
pyyt/get_directory.py
pyyt/main.py
pyyt/main_commandLine.py
pyyt/save_to_json.py
pyyt/url_check.py
pyytdl-1.3.2.dist-info/LICENCE
pyytdl-1.3.2.dist-info/METADATA
pyytdl-1.3.2.dist-info/WHEEL
pyytdl-1.3.2.dist-info/top_level.txt
pyytdl-1.3.2.dist-info/RECORD
