Metadata-Version: 2.1
Name: pyytdl
Version: 1.3.2
Summary: yt_downloader packaged
Home-page: https://github.com/MatiuDev/yt_downloader
Author: MatiuDev
Author-email: matias.devacc@gmail.com
License: MIT
Platform: UNKNOWN
License-File: LICENCE
Requires-Dist: yt-dlp
